taha_qa_sdk-1.2.3.dist-info/licenses/LICENSE
testapi/__init__.py
testapi/api_helper.py
testapi/configuration.py
testapi/testapi_client.py
testapi/controllers/__init__.py
testapi/controllers/api_controller.py
testapi/controllers/base_controller.py
testapi/exceptions/__init__.py
testapi/exceptions/api_exception.py
testapi/http/__init__.py
testapi/http/http_call_back.py
testapi/http/http_method_enum.py
testapi/http/http_request.py
testapi/http/http_response.py
testapi/models/__init__.py
testapi/models/users_request.py
testapi/models/users_response.py
testapi/models/users_response_1.py
testapi/utilities/__init__.py
testapi/utilities/file_wrapper.py
taha_qa_sdk-1.2.3.dist-info/METADATA
taha_qa_sdk-1.2.3.dist-info/WHEEL
taha_qa_sdk-1.2.3.dist-info/top_level.txt
taha_qa_sdk-1.2.3.dist-info/RECORD
