Metadata-Version: 2.4
Name: taha-qa-sdk
Version: 1.2.3
Summary: taha qa
Author-email: taha qa <taha.ali@apimatic.io>
Project-URL: Documentation, https://app.dev.apimatic.io/Account/Login?ReturnUrl=%2Fdashboard
Keywords: SDK
Requires-Python: >=3.7
License-File: LICENSE
Requires-Dist: apimatic-core>=0.2.17,~=0.2.0
Requires-Dist: apimatic-core-interfaces>=0.1.5,~=0.1.0
Requires-Dist: apimatic-requests-client-adapter>=0.1.6,~=0.1.0
Provides-Extra: testutils
Requires-Dist: pytest>=7.2.2; extra == "testutils"
Dynamic: license-file
